[
    {
        "timestamp": "2025-02-03T21:44:34.637082",
        "level": "WARNING",
        "message": " * Debugger is active!",
        "method": "N/A",
        "endpoint": "N/A",
        "ip": "N/A"
    },
    {
        "timestamp": "2025-02-03T21:44:34.637745",
        "level": "WARNING",
        "message": " * Debugger is active!",
        "method": "N/A",
        "endpoint": "N/A",
        "ip": "N/A"
    },
    {
        "timestamp": "2025-02-03T21:44:34.644137",
        "level": "INFO",
        "message": " * Debugger PIN: 980-034-558",
        "method": "N/A",
        "endpoint": "N/A",
        "ip": "N/A"
    },
    {
        "timestamp": "2025-02-03T21:44:34.644850",
        "level": "INFO",
        "message": " * Debugger PIN: 980-034-558",
        "method": "N/A",
        "endpoint": "N/A",
        "ip": "N/A"
    }
]